test/Makefile
test/__init__.py
test/data/highlight-310.right
test/data/highlight-38.right
test/data/highlight-pyp35.right
test/data/highlight-pypy.right
test/data/highlight.cmd
test/data/highlight.right
test/data/macro-pypy.right
test/data/macro-pypy35.right
test/data/macro.cmd
test/data/macro.right
test/data/noscript-pypy.right
test/data/noscript.cmd
test/data/noscript.right
test/data/step-310.right
test/data/step-311.right
test/data/step-38.right
test/data/step-pypy.right
test/data/step.cmd
test/data/step.right
test/example/bug.py
test/example/eval.py
test/example/fib-exec.py
test/example/fib.py
test/example/gcd-breakpoint.py
test/example/gcd-dbgcall-explicit-profile.py
test/example/gcd-dbgcall-noprofile.py
test/example/gcd-dbgcall.py
test/example/gcd.py
test/example/hanoi.py
test/example/multi-line.py
test/example/tail.py
test/functional/__init__.py
test/functional/fn_helper.py
test/functional/stringarray.py
test/functional/test_break.py
test/functional/test_finish.py
test/functional/test_jump.py
test/functional/test_next.py
test/functional/test_sig.py
test/functional/test_skip.py
test/functional/test_step.py
test/functional/example/jump.py
test/functional/example/skip.py
test/functional/example/step/step_computed_value.py
test/functional/example/step/test_skip.py
test/integration/helper.py
test/integration/setup.py
test/integration/test-general.py
test/integration/test_highlight.py
test/integration/test_noscript.py
test/integration/test_step.py
test/integration/.eggs/nose-1.3.7-py3.9.egg/nose/__init__.py
test/integration/.eggs/nose-1.3.7-py3.9.egg/nose/__main__.py
test/integration/.eggs/nose-1.3.7-py3.9.egg/nose/case.py
test/integration/.eggs/nose-1.3.7-py3.9.egg/nose/commands.py
test/integration/.eggs/nose-1.3.7-py3.9.egg/nose/config.py
test/integration/.eggs/nose-1.3.7-py3.9.egg/nose/core.py
test/integration/.eggs/nose-1.3.7-py3.9.egg/nose/exc.py
test/integration/.eggs/nose-1.3.7-py3.9.egg/nose/failure.py
trepan3k-1.5.0.dist-info/licenses/COPYING
trepan3k-1.5.0.dist-info/METADATA
trepan3k-1.5.0.dist-info/WHEEL
trepan3k-1.5.0.dist-info/entry_points.txt
trepan3k-1.5.0.dist-info/top_level.txt
trepan3k-1.5.0.dist-info/RECORD
