Metadata-Version: 2.4
Name: trepan3k
Version: 1.5.0
Summary: GDB-like Python Debugger in the Trepan family
Author-email: Rocky Bernstein <rb@dustyfeet.com>
License-Expression: GPL-3.0-or-later
Project-URL: Homepage, https://pypi.org/project/trepan3k/
Project-URL: Downloads, https://github.com/rocky/python-trepan3k/releases
Keywords: Python bytecode,bytecode,disassembler
Classifier: Development Status :: 5 - Production/Stable
Classifier: Environment :: Console
Classifier: Intended Audience :: Developers
Classifier: Operating System :: OS Independent
Classifier: Programming Language :: Python
Classifier: Topic :: Software Development :: Debuggers
Classifier: Topic :: Software Development :: Libraries :: Python Modules
Classifier: Programming Language :: Python :: 3.0
Classifier: Programming Language :: Python :: 3.1
Classifier: Programming Language :: Python :: 3.2
Classifier: Programming Language :: Python :: 3.3
Classifier: Programming Language :: Python :: 3.4
Classifier: Programming Language :: Python :: 3.5
Classifier: Programming Language :: Python :: 3.6
Classifier: Programming Language :: Python :: 3.7
Classifier: Programming Language :: Python :: 3.8
Classifier: Programming Language :: Python :: 3.9
Classifier: Programming Language :: Python :: 3.10
Classifier: Programming Language :: Python :: 3.11
Classifier: Programming Language :: Python :: 3.12
Classifier: Programming Language :: Python :: 3.13
Classifier: Programming Language :: Python :: Implementation :: PyPy
License-File: COPYING
Requires-Dist: columnize>=0.3.10
Requires-Dist: pyficache>=2.5.0
Requires-Dist: xdis<6.2.0,>=6.1.5
Requires-Dist: Pygments>=2.2.0
Requires-Dist: spark_parser<1.9.2,>=1.8.9
Requires-Dist: tracer>1.9.0
Requires-Dist: term-background>=1.0.2
Provides-Extra: dev
Requires-Dist: flake8; extra == "dev"
Requires-Dist: pre-commit; extra == "dev"
Requires-Dist: pytest; extra == "dev"
Provides-Extra: full
Requires-Dist: prompt-toolkit; extra == "full"
Dynamic: license-file
